pytispark/__init__.py
pytispark/pytispark.py
pytispark-2.0.dist-info/METADATA
pytispark-2.0.dist-info/WHEEL
pytispark-2.0.dist-info/top_level.txt
pytispark-2.0.dist-info/RECORD
