Metadata-Version: 2.1
Name: pytispark
Version: 2.0
Summary: TiSpark support for python
Home-page: https://github.com/pingcap/tispark
Author: PingCAP
Author-email: novemser@gmail.com
License: Apache 2.0
Keywords: tispark,spark,tidb,olap
Platform: UNKNOWN
Classifier: Development Status :: 3 - Alpha
Classifier: Intended Audience :: Developers
Classifier: Programming Language :: Python :: 2
Classifier: Programming Language :: Python :: 2.7
Classifier: Programming Language :: Python :: 3
Classifier: Programming Language :: Python :: 3.3
Classifier: Programming Language :: Python :: 3.4
Classifier: Programming Language :: Python :: 3.5
Requires-Dist: pyspark (==2.3.3)
Requires-Dist: py4j (==0.10.7)
